MANIFEST.in
README.md
requirements.txt
setup.py
dxh_django/__init__.py
dxh_django/__version__.py
dxh_django/decorator.py
dxh_django/generator.py
dxh_django/headers.py
dxh_django/main.py
dxh_django/middleware.py
dxh_django/response.py
dxh_django/utilities.py
dxh_django/validators.py
dxh_django.egg-info/PKG-INFO
dxh_django.egg-info/SOURCES.txt
dxh_django.egg-info/dependency_links.txt
dxh_django.egg-info/requires.txt
dxh_django.egg-info/top_level.txt
dxh_django/anticaptcha/__init__.py
dxh_django/anticaptcha/captcha.py
dxh_django/aws/__init__.py
dxh_django/aws/s3_client.py
dxh_django/aws/textract.py
dxh_django/config/__init__.py
dxh_django/config/settings.py