Metadata-Version: 2.1
Name: dxh-django
Version: 0.1.0
Summary: A Django package for development
Home-page: https://github.com/devxhub/dxh-django
Author: DEVxHUB
License: MIT
Project-URL: Source, https://github.com/devxhub/dxh-django
Keywords: python,django,package,development,devxhub,dxh-django,dxh,devxhub-django
Platform: UNKNOWN
Classifier: Development Status :: 4 - Beta
Classifier: Intended Audience :: Developers
Classifier: License :: OSI Approved :: BSD License
Classifier: Natural Language :: English
Classifier: Operating System :: OS Independent
Classifier: Programming Language :: Python
Classifier: Programming Language :: Python :: 3
Classifier: Programming Language :: Python :: 3.11
Classifier: Programming Language :: Python :: Implementation :: CPython
Classifier: Topic :: Software Development
Classifier: Topic :: Software Development :: Libraries :: Python Modules
Requires-Python: >=3.9
